numfi/__init__.py
numfi/numfi.py
numfi/test.py
numfi-0.5.0.dist-info/LICENSE
numfi-0.5.0.dist-info/METADATA
numfi-0.5.0.dist-info/WHEEL
numfi-0.5.0.dist-info/top_level.txt
numfi-0.5.0.dist-info/RECORD
