Metadata-Version: 2.1
Name: numfi
Version: 0.5.0
Summary: a numpy.ndarray subclass that does fixed-point arithmetic
Home-page: https://github.com/ZZZZzzzzac/numfi
Author: ZinGer_KyoN
Author-email: zinger.kyon@gmail.com
License: MIT
Project-URL: Bug Tracker, https://github.com/ZZZZzzzzac/numfi/issues
Classifier: Programming Language :: Python :: 3
Classifier: License :: OSI Approved :: MIT License
Classifier: Operating System :: OS Independent
Requires-Python: >=3.6
License-File: LICENSE
Requires-Dist: numpy
